.gitignore
.pre-commit-config.yaml
CMakeLists.txt
LICENSE
README.md
example.ipynb
example_verification.ipynb
example_zip.ipynb
foobar.py
pyproject.toml
setup.py
test_instances.zip
test_solutions.zip
.github/workflows/pytest_linux.yml
.github/workflows/pytest_windows.yml
.github/workflows/release.yml
cmake/CPM.cmake
src/CMakeLists.txt
src/cgshop2026_pyutils/CMakeLists.txt
src/cgshop2026_pyutils/__init__.py
src/cgshop2026_pyutils/verify.py
src/cgshop2026_pyutils/visualize.py
src/cgshop2026_pyutils.egg-info/PKG-INFO
src/cgshop2026_pyutils.egg-info/SOURCES.txt
src/cgshop2026_pyutils.egg-info/dependency_links.txt
src/cgshop2026_pyutils.egg-info/requires.txt
src/cgshop2026_pyutils.egg-info/top_level.txt
src/cgshop2026_pyutils/geometry/CMakeLists.txt
src/cgshop2026_pyutils/geometry/__init__.py
src/cgshop2026_pyutils/geometry/_bindings.cpp
src/cgshop2026_pyutils/geometry/cgal_types.h
src/cgshop2026_pyutils/geometry/cgal_utils.cpp
src/cgshop2026_pyutils/geometry/cgal_utils.h
src/cgshop2026_pyutils/geometry/draw.py
src/cgshop2026_pyutils/geometry/flip_partner_map.py
src/cgshop2026_pyutils/geometry/flippable_triangulation.py
src/cgshop2026_pyutils/geometry/geometry_operations.cpp
src/cgshop2026_pyutils/geometry/geometry_operations.h
src/cgshop2026_pyutils/geometry/integral_points.h
src/cgshop2026_pyutils/geometry/triangulation_validation.cpp
src/cgshop2026_pyutils/geometry/triangulation_validation.h
src/cgshop2026_pyutils/instance_database/__init__.py
src/cgshop2026_pyutils/instance_database/instance_base_database.py
src/cgshop2026_pyutils/instance_database/instance_database.py
src/cgshop2026_pyutils/instance_database/instance_file_database.py
src/cgshop2026_pyutils/instance_database/instance_zip_database.py
src/cgshop2026_pyutils/io/__init__.py
src/cgshop2026_pyutils/schemas/__init__.py
src/cgshop2026_pyutils/schemas/instance.py
src/cgshop2026_pyutils/schemas/solution.py
src/cgshop2026_pyutils/zip/__init__.py
src/cgshop2026_pyutils/zip/zip_processor.py
src/cgshop2026_pyutils/zip/zip_reader_errors.py
src/cgshop2026_pyutils/zip/zip_writer.py
tests/test_verify.py
tests/geometry/test_compute_triangles.py
tests/geometry/test_do_cross.py
tests/geometry/test_flip_partner_map.py
