Metadata-Version: 2.4
Name: cgshop2026_pyutils
Version: 0.3.1
Summary: Utilities for verifying solutions of the CG:SHOP 2026 Competition.
Author: Dominik Krupke
License: LICENSE
Requires-Python: >=3.10
License-File: LICENSE
Requires-Dist: matplotlib
Requires-Dist: numpy
Requires-Dist: chardet>=4.0.0
Requires-Dist: networkx>=2.0.0
Requires-Dist: pydantic>=2.0.0
Dynamic: author
Dynamic: description
Dynamic: description-content-type
Dynamic: license
Dynamic: license-file
Dynamic: requires-dist
Dynamic: requires-python
Dynamic: summary
